[
    {
        "col0": 1,
        "col1": "npc_charavoice-10000001",
        "col2": "_HELLO_JP",
        "col3": 0,
        "col4": "",
        "col5": "",
        "col6": ""
    },
    {
        "col0": 2,
        "col1": "npc_charavoice-10000002",
        "col2": "_DIALOGUE1_JP",
        "col3": 0,
        "col4": "",
        "col5": "",
        "col6": ""
    },
    {
        "col0": 3,
        "col1": "npc_charavoice-10000003",
        "col2": "_DIALOGUE2_JP",
        "col3": 0,
        "col4": "",
        "col5": "",
        "col6": ""
    },
    {
        "col0": 4,
        "col1": "npc_charavoice-10000004",
        "col2": "_DIALOGUE3_JP",
        "col3": 0,
        "col4": "",
        "col5": "",
        "col6": ""
    },
    {
        "col0": 5,
        "col1": "npc_charavoice-10000005",
        "col2": "_DIALOGUE4_JP",
        "col3": 0,
        "col4": "",
        "col5": "",
        "col6": ""
    },
    {
        "col0": 6,
        "col1": "npc_charavoice-10000006",
        "col2": "_DIALOGUE5_JP",
        "col3": 0,
        "col4": "",
        "col5": "",
        "col6": ""
    },
    {
        "col0": 7,
        "col1": "npc_charavoice-10000007",
        "col2": "_DIALOGUE6_JP",
        "col3": 0,
        "col4": "",
        "col5": "",
        "col6": ""
    },
    {
        "col0": 8,
        "col1": "npc_charavoice-10000008",
        "col2": "_DIALOGUE7_JP",
        "col3": 0,
        "col4": "",
        "col5": "",
        "col6": ""
    },
    {
        "col0": 9,
        "col1": "npc_charavoice-10000009",
        "col2": "_DIALOGUE8_JP",
        "col3": 0,
        "col4": "",
        "col5": "",
        "col6": ""
    },
    {
        "col0": 10,
        "col1": "npc_charavoice-10000010",
        "col2": "_DIALOGUE9_JP",
        "col3": 0,
        "col4": "",
        "col5": "",
        "col6": ""
    },
    {
        "col0": 11,
        "col1": "npc_charavoice-10000011",
        "col2": "_DIALOGUE10_JP",
        "col3": 0,
        "col4": "",
        "col5": "",
        "col6": ""
    },
    {
        "col0": 12,
        "col1": "npc_charavoice-10000012",
        "col2": "BUILDOVER_JP",
        "col3": 0,
        "col4": "",
        "col5": "",
        "col6": ""
    },
    {
        "col0": 13,
        "col1": "npc_charavoice-10000013",
        "col2": "_NEWYEAR_JP",
        "col3": 0,
        "col4": "",
        "col5": "01-01|01-02|01-03",
        "col6": ""
    },
    {
        "col0": 14,
        "col1": "npc_charavoice-10000014",
        "col2": "_VALENTINE_JP",
        "col3": 0,
        "col4": "02-14",
        "col5": "",
        "col6": ""
    },
    {
        "col0": 15,
        "col1": "npc_charavoice-10000015",
        "col2": "_TANABATA_JP",
        "col3": 0,
        "col4": "",
        "col5": "07-07",
        "col6": ""
    },
    {
        "col0": 16,
        "col1": "npc_charavoice-10000016",
        "col2": "_ALLHALLOWS_JP",
        "col3": 0,
        "col4": "10-31|11-01",
        "col5": "",
        "col6": ""
    },
    {
        "col0": 17,
        "col1": "npc_charavoice-10000017",
        "col2": "_CHRISTMAS_JP",
        "col3": 0,
        "col4": "12-24|12-25",
        "col5": "",
        "col6": ""
    },
    {
        "col0": 18,
        "col1": "npc_charavoice-10000018",
        "col2": "_MORNING_JP",
        "col3": 0,
        "col4": "",
        "col5": "",
        "col6": "06:30:01-08:00:00|09:00:01-09:30:00"
    },
    {
        "col0": 19,
        "col1": "npc_charavoice-10000019",
        "col2": "_NOON_JP",
        "col3": 0,
        "col4": "",
        "col5": "",
        "col6": "11:00:01-11:30:00|13:00:01-13:30:00"
    },
    {
        "col0": 20,
        "col1": "npc_charavoice-10000020",
        "col2": "_AFTERNOON_JP",
        "col3": 0,
        "col4": "",
        "col5": "",
        "col6": "14:00:01-16:00:00"
    },
    {
        "col0": 21,
        "col1": "npc_charavoice-10000021",
        "col2": "_EVENING_JP",
        "col3": 0,
        "col4": "",
        "col5": "",
        "col6": "20:00:01-21:30:00"
    },
    {
        "col0": 22,
        "col1": "npc_charavoice-10000022",
        "col2": "_MIDNIGHT_JP",
        "col3": 0,
        "col4": "",
        "col5": "",
        "col6": "23:45:01-23:59:59|00:00:00-00:15:00|03:00:01-06:30:00"
    },
    {
        "col0": 23,
        "col1": "npc_charavoice-10000023",
        "col2": "_BREAKFAST_JP",
        "col3": 0,
        "col4": "",
        "col5": "",
        "col6": "08:00:01-09:00:00"
    },
    {
        "col0": 24,
        "col1": "npc_charavoice-10000024",
        "col2": "_LUNCH_JP",
        "col3": 0,
        "col4": "",
        "col5": "",
        "col6": "11:30:01-13:00:00"
    },
    {
        "col0": 25,
        "col1": "npc_charavoice-10000025",
        "col2": "_DINNRER_JP",
        "col3": 0,
        "col4": "",
        "col5": "",
        "col6": "17:30:01-19:00:00"
    },
    {
        "col0": 26,
        "col1": "npc_charavoice-10000026",
        "col2": "_SUPPER_JP",
        "col3": 0,
        "col4": "",
        "col5": "",
        "col6": "22:30:01-23:45:00|00:15:01-01:15:00"
    },
    {
        "col0": 27,
        "col1": "npc_charavoice-10000027",
        "col2": "_AMUSEMENT_JP",
        "col3": 0,
        "col4": "",
        "col5": "",
        "col6": "21:30:01-22:30:00|01:15:01-03:00:00"
    },
    {
        "col0": 28,
        "col1": "npc_charavoice-10000028",
        "col2": "_CONTRIBUTION1_JP",
        "col3": 5,
        "col4": "",
        "col5": "",
        "col6": ""
    },
    {
        "col0": 29,
        "col1": "npc_charavoice-10000029",
        "col2": "_CONTRIBUTION2_JP",
        "col3": 10,
        "col4": "",
        "col5": "",
        "col6": ""
    },
    {
        "col0": 30,
        "col1": "npc_charavoice-10000030",
        "col2": "_CONTRIBUTION3_JP",
        "col3": 10,
        "col4": "",
        "col5": "",
        "col6": ""
    },
    {
        "col0": 31,
        "col1": "npc_charavoice-10000031",
        "col2": "_CONTRIBUTION4_JP",
        "col3": 15,
        "col4": "",
        "col5": "",
        "col6": ""
    },
    {
        "col0": 32,
        "col1": "npc_charavoice-10000032",
        "col2": "_CONTRIBUTION5_JP",
        "col3": 15,
        "col4": "",
        "col5": "",
        "col6": ""
    },
    {
        "col0": 33,
        "col1": "npc_charavoice-10000033",
        "col2": "_CONTRIBUTION6_JP",
        "col3": 20,
        "col4": "",
        "col5": "",
        "col6": ""
    },
    {
        "col0": 34,
        "col1": "npc_charavoice-10000034",
        "col2": "_CONTRIBUTION7_JP",
        "col3": 20,
        "col4": "",
        "col5": "",
        "col6": ""
    },
    {
        "col0": 35,
        "col1": "npc_charavoice-10000035",
        "col2": "_CONTRIBUTION8_JP",
        "col3": 20,
        "col4": "",
        "col5": "",
        "col6": ""
    },
    {
        "col0": 36,
        "col1": "npc_charavoice-10000036",
        "col2": "_CONTRIBUTION9_JP",
        "col3": 25,
        "col4": "",
        "col5": "",
        "col6": ""
    },
    {
        "col0": 37,
        "col1": "npc_charavoice-10000037",
        "col2": "_CONTRIBUTION10_JP",
        "col3": 25,
        "col4": "",
        "col5": "",
        "col6": ""
    },
    {
        "col0": 38,
        "col1": "npc_charavoice-10000038",
        "col2": "_CONTRIBUTION11_JP",
        "col3": 25,
        "col4": "",
        "col5": "",
        "col6": ""
    },
    {
        "col0": 39,
        "col1": "npc_charavoice-10000039",
        "col2": "_CONTRIBUTION12_JP",
        "col3": 30,
        "col4": "",
        "col5": "",
        "col6": ""
    },
    {
        "col0": 40,
        "col1": "npc_charavoice-10000040",
        "col2": "_CONTRIBUTION13_JP",
        "col3": 30,
        "col4": "",
        "col5": "",
        "col6": ""
    },
    {
        "col0": 41,
        "col1": "npc_charavoice-10000041",
        "col2": "_CONTRIBUTION14_JP",
        "col3": 30,
        "col4": "",
        "col5": "",
        "col6": ""
    },
    {
        "col0": 42,
        "col1": "npc_charavoice-10000042",
        "col2": "_CONTRIBUTION15_JP",
        "col3": 30,
        "col4": "",
        "col5": "",
        "col6": ""
    }
]