[
    {
        "id": 3001,
        "trigger_target_type": "",
        "trigger_range": "",
        "trigger_formula": "",
        "target_type": "4,5,6",
        "target_range": 2,
        "battle_skill": "610004",
        "code": "SpotTarget0"
    },
    {
        "id": 3002,
        "trigger_target_type": "",
        "trigger_range": "",
        "trigger_formula": "",
        "target_type": "1,2,3,8",
        "target_range": 3,
        "battle_skill": "610005",
        "code": "SpotTarget0"
    },
    {
        "id": 3003,
        "trigger_target_type": "1,2,3,8",
        "trigger_range": "1",
        "trigger_formula": "<2",
        "target_type": "8",
        "target_range": 0,
        "battle_skill": "610006",
        "code": "SpotTarget0"
    },
    {
        "id": 3004,
        "trigger_target_type": "",
        "trigger_range": "",
        "trigger_formula": "",
        "target_type": "8",
        "target_range": 0,
        "battle_skill": "610007",
        "code": "SpotTarget0"
    },
    {
        "id": 3005,
        "trigger_target_type": "1,2,3,8;1,2,3,8",
        "trigger_range": "3;3",
        "trigger_formula": "<5;>1",
        "target_type": "1",
        "target_range": 0,
        "battle_skill": "199001",
        "code": "SpotTarget0"
    },
    {
        "id": 3006,
        "trigger_target_type": "4,5,6;1,2,3,8",
        "trigger_range": "2;3",
        "trigger_formula": "<0;>0",
        "target_type": "1,2,3,8",
        "target_range": 3,
        "battle_skill": "199001",
        "code": "SpotTarget0"
    },
    {
        "id": 3007,
        "trigger_target_type": "",
        "trigger_range": "",
        "trigger_formula": "",
        "target_type": "8",
        "target_range": 0,
        "battle_skill": "610008",
        "code": "SpotTarget0"
    },
    {
        "id": 3008,
        "trigger_target_type": "",
        "trigger_range": "",
        "trigger_formula": "",
        "target_type": "1,2,3,8",
        "target_range": 2,
        "battle_skill": "610009",
        "code": "SpotTarget0"
    }
]